flask_shopify_utils/__init__.py
flask_shopify_utils/model.py
flask_shopify_utils/utils.py
flask_shopify_utils/cli/__init__.py
flask_shopify_utils/cli/main.py
flask_shopify_utils-0.2.6.dist-info/METADATA
flask_shopify_utils-0.2.6.dist-info/WHEEL
flask_shopify_utils-0.2.6.dist-info/entry_points.txt
flask_shopify_utils-0.2.6.dist-info/licenses/LICENSE
flask_shopify_utils-0.2.6.dist-info/RECORD
