Metadata-Version: 2.4
Name: flask-shopify-utils
Version: 0.2.6
Summary: A Flask extension for Shopify app development
Project-URL: Homepage, https://github.com/leocxy/flask-shopify-utils
Project-URL: Bug Tracker, https://github.com/leocxy/flask-shopify-utils/issues
Author: Leo Chen
Author-email: leo.cxy88@gmail.com
Maintainer: Leo Chen
Maintainer-email: leo.cxy88@gmail.com
License-File: LICENSE
Keywords: Extension,Flask,Flask Extension,SDK,Shopify,Shopify-SDK
Classifier: Development Status :: 3 - Alpha
Classifier: Framework :: Flask
Classifier: Intended Audience :: Developers
Classifier: Programming Language :: Python :: 3.9
Classifier: Programming Language :: Python :: 3.10
Classifier: Programming Language :: Python :: 3.11
Classifier: Programming Language :: Python :: 3.12
Classifier: Topic :: Software Development :: Libraries :: Python Modules
Requires-Python: >=3.9
Requires-Dist: cerberus<2
Requires-Dist: flask-sqlalchemy<4
Requires-Dist: flask<4
Requires-Dist: psutil<8
Requires-Dist: pyjwt<3
Requires-Dist: pytz==2025.2
Requires-Dist: requests<3
Requires-Dist: sgqlc<17
Requires-Dist: simplejson<4
Provides-Extra: dev
Requires-Dist: build==1.2.1; extra == 'dev'
Requires-Dist: flake8<8; extra == 'dev'
Requires-Dist: pytest<9; extra == 'dev'
Requires-Dist: twine<7; extra == 'dev'
